digipics/NextCloud.py
digipics/__init__.py
digipics/common.py
digipics/digiimport.py
digipics/digiphone.py
digipics/test_digiimport.py
digipics-0.6.dist-info/LICENSE
digipics-0.6.dist-info/METADATA
digipics-0.6.dist-info/WHEEL
digipics-0.6.dist-info/entry_points.txt
digipics-0.6.dist-info/top_level.txt
digipics-0.6.dist-info/RECORD
