Metadata-Version: 2.1
Name: digipics
Version: 0.6
Summary: Organize your digital pictures
Author-email: Stephan Skrodzki <skrodzki@stevekist.de>
License: GNU AFFERO GENERAL PUBLIC LICENSE
Project-URL: repository, https://gitlab.com/steviehs/digipics
Classifier: Programming Language :: Python :: 3
Classifier: License :: OSI Approved :: GNU Affero General Public License v3
Classifier: Operating System :: OS Independent
Requires-Python: >=3.7
License-File: LICENSE
